{
  "users": [
    {
      "id": "dd84",
      "name": "rajeev anand",
      "email": "anandrajeev1234@gmail.com",
      "pass": "123456",
      "isAdmin": false
    },
    {
      "id": "7f56",
      "name": "idk2",
      "email": "ok@ok.com",
      "pass": "123456",
      "isAdmin": false
    },
    {
      "id": "5fa7",
      "name": "rajeev",
      "email": "test@example.com",
      "pass": "123456",
      "isAdmin": false
    }
  ],
  "products": [
    {
      "id": "1",
      "title": "Fjallraven _ Foldsack No. 1 Backpack, Fits 15 Laptops",
      "price": 109.95,
      "description": "Your perfect pack for everyday use and walks in the forest. Stash your laptop (up to 15 inches) in the padded sleeve, your everyday",
      "category": "men's clothing",
      "image": "https://fakestoreapi.com/img/81fPKd-2AYL._AC_SL1500_t.png",
      "rating": {
        "rate": 3.9,
        "count": 120
      }
    }
  ],
  "carts": []
}